great_expectations_provider/__init__.py
great_expectations_provider/example_dags/__init__.py
great_expectations_provider/example_dags/example_great_expectations_dag.py
great_expectations_provider/operators/__init__.py
great_expectations_provider/operators/great_expectations.py
include/great_expectations/object_configs/__init__.py
include/great_expectations/object_configs/example_checkpoint_config.py
include/great_expectations/object_configs/example_data_context_config.py
include/great_expectations/object_configs/example_runtime_batch_request_for_plugin_expectation.py
include/great_expectations/plugins/__init__.py
include/great_expectations/plugins/expectations/__init__.py
include/great_expectations/plugins/expectations/expect_column_values_to_be_alphabetical.py
tests/__init__.py
tests/operators/__init__.py
tests/operators/test_great_expectations.py
airflow_provider_great_expectations-0.2.9.dist-info/LICENSE.txt
airflow_provider_great_expectations-0.2.9.dist-info/METADATA
airflow_provider_great_expectations-0.2.9.dist-info/WHEEL
airflow_provider_great_expectations-0.2.9.dist-info/entry_points.txt
airflow_provider_great_expectations-0.2.9.dist-info/top_level.txt
airflow_provider_great_expectations-0.2.9.dist-info/RECORD
