Metadata-Version: 2.1
Name: airflow-provider-great-expectations
Version: 0.2.9
Summary: An Apache Airflow provider for Great Expectations
Home-page: https://github.com/astronomer/airflow-provider-great-expectations
Author: Great Expectations & Astronomer
Author-email: humans@astronomer.io
License: Apache License 2.0
Project-URL: Source Code, https://github.com/astronomer/airflow-provider-great-expectations
Project-URL: Changelog, https://github.com/astronomer/airflow-provider-great-expectations/blob/main/CHANGELOG.md
Classifier: Development Status :: 5 - Production/Stable
Classifier: Environment :: Web Environment
Classifier: Framework :: Apache Airflow
Classifier: Framework :: Apache Airflow :: Provider
Classifier: Intended Audience :: Developers
Classifier: License :: OSI Approved :: Apache Software License
Classifier: Operating System :: OS Independent
Classifier: Programming Language :: Python
Classifier: Programming Language :: Python :: 3
Classifier: Programming Language :: Python :: 3.6
Classifier: Programming Language :: Python :: 3.7
Classifier: Programming Language :: Python :: 3.8
Classifier: Programming Language :: Python :: 3.9
Classifier: Programming Language :: Python :: 3.10
Requires-Python: >=3.6
License-File: LICENSE.txt
Requires-Dist: apache-airflow>=2.1
Requires-Dist: great-expectations<1.0.0,>=0.15.34
Requires-Dist: sqlalchemy>=1.3.16
Provides-Extra: tests
Requires-Dist: parameterized; extra == "tests"
Requires-Dist: pytest; extra == "tests"
Requires-Dist: pytest-mock; extra == "tests"
Requires-Dist: apache-airflow-providers-snowflake>=3.3.0; extra == "tests"
